django_remote_finder-0.5.dist-info/licenses/LICENSE
remote_finder/__init__.py
django_remote_finder-0.5.dist-info/METADATA
django_remote_finder-0.5.dist-info/WHEEL
django_remote_finder-0.5.dist-info/top_level.txt
django_remote_finder-0.5.dist-info/RECORD
