Metadata-Version: 2.4
Name: django-remote-finder
Version: 0.5
Summary: Keep various JavaScript/CSS libraries updated within a Django package
Author: Jim Garrison
Maintainer-email: Claude Paroz <claude@2xlibre.net>
License-Expression: MIT
Project-URL: Homepage, https://github.com/claudep/django-remote-finder
Classifier: Development Status :: 4 - Beta
Classifier: Environment :: Web Environment
Classifier: Framework :: Django
Classifier: Intended Audience :: Developers
Classifier: Operating System :: OS Independent
Classifier: Programming Language :: Python
Classifier: Programming Language :: Python :: 3
Classifier: Topic :: Internet :: WWW/HTTP
Classifier: Topic :: Software Development :: Libraries :: Python Modules
Requires-Python: >=3.9
License-File: LICENSE
Requires-Dist: django>4.2
Dynamic: license-file
